Metadata-Version: 1.0
Name: yos
Version: 1.0.1
Summary: this is yos
Home-page: http://www.yos.com
Author: yos
Author-email: yos@gmial.com
License: UNKNOWN
Platform: UNKNOWN
